nxt/__init__.py
nxt/backend/__init__.py
nxt/backend/bluetooth.py
nxt/backend/devfile.py
nxt/backend/socket.py
nxt/backend/usb.py
nxt/brick.py
nxt/command/__init__.py
nxt/command/push.py
nxt/command/screenshot.py
nxt/command/server.py
nxt/command/test.py
nxt/conftest.py
nxt/error.py
nxt/locator.py
nxt/motcont.py
nxt/motor.py
nxt/sensor/__init__.py
nxt/sensor/analog.py
nxt/sensor/digital.py
nxt/sensor/generic.py
nxt/sensor/hitechnic.py
nxt/sensor/mindsensors.py
nxt/telegram.py
nxt_python-3.5.1.dist-info/LICENSE
nxt_python-3.5.1.dist-info/METADATA
nxt_python-3.5.1.dist-info/WHEEL
nxt_python-3.5.1.dist-info/entry_points.txt
nxt_python-3.5.1.dist-info/RECORD
