Metadata-Version: 2.1
Name: nxt-python
Version: 3.5.1
Summary: LEGO Mindstorms NXT Control Package
Home-page: https://sr.ht/~ni/nxt-python/
License: GPL-3.0-or-later
Author: Nicolas Schodet
Author-email: nico@ni.fr.eu.org
Requires-Python: >=3.9,<4.0
Classifier: License :: OSI Approved :: GNU General Public License v3 or later (GPLv3+)
Classifier: Programming Language :: Python :: 3
Classifier: Programming Language :: Python :: 3.9
Classifier: Programming Language :: Python :: 3.10
Classifier: Programming Language :: Python :: 3.11
Provides-Extra: bluetooth
Provides-Extra: screenshot
Requires-Dist: pillow (>=9.4.0,<10.0.0) ; extra == "screenshot"
Requires-Dist: pybluez (>=0.23,<0.24) ; extra == "bluetooth"
Requires-Dist: pyusb (>=1.2.1,<2.0.0)
Project-URL: Documentation, https://ni.srht.site/nxt-python/latest/
Project-URL: Repository, https://git.sr.ht/~ni/nxt-python
